testy.py
testy_command_line-0.8.1.dist-info/METADATA
testy_command_line-0.8.1.dist-info/WHEEL
testy_command_line-0.8.1.dist-info/entry_points.txt
testy_command_line-0.8.1.dist-info/top_level.txt
testy_command_line-0.8.1.dist-info/RECORD
