Metadata-Version: 2.4
Name: testy-command-line
Version: 0.8.1
Summary: A Testing Script/Module for Command-line Programs
Author-email: Chris Kauffman <kauffman77@gmail.com>
Maintainer-email: Chris Kauffman <kauffman77@gmail.com>
License-Expression: GPL-3.0-or-later
Project-URL: Homepage, https://github.com/kauffman77/testy
Keywords: testing
Requires-Python: >=3.8
Provides-Extra: dev
Provides-Extra: test
